vior/__init__.py
vior/secrets/__init__.py
vior/secrets/client.py
vior/secrets/exceptions.py
vior_sdk-0.1.1.dist-info/licenses/LICENSE
vior_sdk-0.1.1.dist-info/METADATA
vior_sdk-0.1.1.dist-info/WHEEL
vior_sdk-0.1.1.dist-info/top_level.txt
vior_sdk-0.1.1.dist-info/RECORD
