Metadata-Version: 2.4
Name: vior-sdk
Version: 0.1.1
Summary: Vior SDK - Python SDK for Vior Secrets management
Author-email: Viorcloud Team <support@viorcloud.com>
License-Expression: MIT
Project-URL: Homepage, https://secrets.viorcloud.com
Project-URL: Documentation, https://secrets.viorcloud.com/docs
Project-URL: Repository, https://github.com/viorcloud/vior-sdk
Keywords: vior,secrets,sdk,api,security
Classifier: Development Status :: 4 - Beta
Classifier: Intended Audience :: Developers
Classifier: Operating System :: OS Independent
Classifier: Programming Language :: Python :: 3
Classifier: Programming Language :: Python :: 3.7
Classifier: Programming Language :: Python :: 3.8
Classifier: Programming Language :: Python :: 3.9
Classifier: Programming Language :: Python :: 3.10
Classifier: Programming Language :: Python :: 3.11
Requires-Python: >=3.7
License-File: LICENSE
Requires-Dist: requests>=2.25.0
Provides-Extra: dev
Requires-Dist: pytest>=6.0; extra == "dev"
Requires-Dist: black>=21.0; extra == "dev"
Requires-Dist: flake8>=3.8; extra == "dev"
Dynamic: license-file
